cyperf/__init__.py
cyperf/api_client.py
cyperf/api_response.py
cyperf/configuration.py
cyperf/dynamic_model_meta.py
cyperf/exceptions.py
cyperf/py.typed
cyperf/rest.py
cyperf/utils.py
cyperf/api/__init__.py
cyperf/api/agents_api.py
cyperf/api/application_resources_api.py
cyperf/api/authorization_api.py
cyperf/api/brokers_api.py
cyperf/api/configurations_api.py
cyperf/api/data_migration_api.py
cyperf/api/diagnostics_api.py
cyperf/api/license_servers_api.py
cyperf/api/licensing_api.py
cyperf/api/notifications_api.py
cyperf/api/reports_api.py
cyperf/api/sessions_api.py
cyperf/api/statistics_api.py
cyperf/api/test_operations_api.py
cyperf/api/test_results_api.py
cyperf/api/utils_api.py
cyperf/dynamic_models/__init__.py
cyperf/models/__init__.py
cyperf/models/action.py
cyperf/models/action_base.py
cyperf/models/action_input.py
cyperf/models/action_input_find_param.py
cyperf/models/action_metadata.py
cyperf/models/activation_code_info.py
cyperf/models/activation_code_list_request.py
cyperf/models/activation_code_request.py
cyperf/models/add_action_info.py
cyperf/models/add_input.py
cyperf/models/advanced_settings.py
cyperf/models/agent.py
cyperf/models/agent_assignment_by_port.py
cyperf/models/agent_assignment_details.py
cyperf/models/agent_assignments.py
cyperf/models/agent_cpu_info.py
cyperf/models/agent_features.py
cyperf/models/agent_optimization_mode.py
cyperf/models/agent_release.py
cyperf/models/agent_reservation.py
cyperf/models/agent_to_be_rebooted.py
cyperf/models/agents_group.py
cyperf/models/api_link.py
cyperf/models/api_relationship.py
cyperf/models/app_exchange.py
cyperf/models/app_flow.py
cyperf/models/app_flow_desc.py
cyperf/models/app_flow_input.py
cyperf/models/app_flow_input_find_param.py
cyperf/models/app_id.py
cyperf/models/app_mode.py
cyperf/models/application.py
cyperf/models/application_profile.py
cyperf/models/application_type.py
cyperf/models/appsec_app.py
cyperf/models/appsec_app_metadata.py
cyperf/models/appsec_attack.py
cyperf-7.0.6.dist-info/licenses/LICENSE
cyperf-7.0.6.dist-info/METADATA
cyperf-7.0.6.dist-info/WHEEL
cyperf-7.0.6.dist-info/top_level.txt
cyperf-7.0.6.dist-info/RECORD
