Metadata-Version: 2.4
Name: cyperf
Version: 7.0.6
Summary: CyPerf REST API
Home-page: 
Author: Keysight CyPerf
Author-email: support@keysight.com
License: MIT License (MIT)
Keywords: cyperf,keysight
License-File: LICENSE
Requires-Dist: urllib3<2.3.0,>=2.2.2
Requires-Dist: python-dateutil
Requires-Dist: pydantic>=2
Requires-Dist: typing-extensions>=4.7.1
Dynamic: author
Dynamic: author-email
Dynamic: description
Dynamic: description-content-type
Dynamic: keywords
Dynamic: license
Dynamic: license-file
Dynamic: requires-dist
Dynamic: summary
